_version.py
paramak/__init__.py
paramak/utils.py
paramak/assemblies/__init__.py
paramak/assemblies/assembly.py
paramak/assemblies/spherical_tokamak.py
paramak/assemblies/tokamak.py
paramak/workplanes/__init__.py
paramak/workplanes/blanket_constant_thickness_arc_h.py
paramak/workplanes/blanket_from_plasma.py
paramak/workplanes/center_column_shield_cylinder.py
paramak/workplanes/constant_thickness_dome.py
paramak/workplanes/cutting_wedge.py
paramak/workplanes/dished_vacuum_vessel.py
paramak/workplanes/plasma_simplified.py
paramak/workplanes/poloidal_field_coil.py
paramak/workplanes/poloidal_field_coil_case.py
paramak/workplanes/toroidal_field_coil_princeton_d.py
paramak/workplanes/toroidal_field_coil_rectangle.py
paramak/workplanes/u_shaped_dome.py
paramak-0.9.8.dist-info/licenses/LICENSE
paramak-0.9.8.dist-info/METADATA
paramak-0.9.8.dist-info/WHEEL
paramak-0.9.8.dist-info/top_level.txt
paramak-0.9.8.dist-info/RECORD
