Metadata-Version: 2.4
Name: paramak
Version: 0.9.8
Summary: Create 3D fusion reactor CAD models based on input parameters
Author: The Paramak Development Team
Project-URL: Homepage, https://github.com/fusion-energy/paramak
Project-URL: Bug Tracker, https://github.com/fusion-energy/paramak/issues
Project-URL: Documentation, https://fusion-energy.github.io/paramak
Keywords: python,geometry,reactor,model,cad,fusion,parametric,dagmc,openmc
Classifier: Programming Language :: Python :: 3
Classifier: License :: OSI Approved :: MIT License
Classifier: Operating System :: OS Independent
Requires-Python: >=3.8
License-File: LICENSE
Requires-Dist: cadquery>=2.5.2
Requires-Dist: numpy
Requires-Dist: mpmath
Requires-Dist: sympy
Requires-Dist: scipy
Provides-Extra: tests
Requires-Dist: pytest>=5.4.3; extra == "tests"
Requires-Dist: pytest-cov>=2.12.1; extra == "tests"
Requires-Dist: dagmc_h5m_file_inspector>=0.5.0; extra == "tests"
Requires-Dist: openmc_data_downloader; extra == "tests"
Provides-Extra: docs
Requires-Dist: sphinx_autodoc_typehints; extra == "docs"
Requires-Dist: openmc_data_downloader; extra == "docs"
Requires-Dist: sphinxcadquery; extra == "docs"
Requires-Dist: sphinx; extra == "docs"
Requires-Dist: pydata-sphinx-theme; extra == "docs"
Requires-Dist: cadquery; extra == "docs"
Requires-Dist: ipython; extra == "docs"
Requires-Dist: sphinx_design; extra == "docs"
Requires-Dist: setuptools; extra == "docs"
Dynamic: license-file
